ddnatlas/__init__.py
ddnatlas/anthropic_prompt.py
ddnatlas/business_metadata.py
ddnatlas/camel_to_title.py
ddnatlas/claude.py
ddnatlas/cli.py
ddnatlas/columns.py
ddnatlas/connector_collections.py
ddnatlas/data_connectors.py
ddnatlas/descriptions.py
ddnatlas/execute_request.py
ddnatlas/fields.py
ddnatlas/generate_subgraph.py
ddnatlas/get_entities.py
ddnatlas/glossary.py
ddnatlas/main.py
ddnatlas/object_types.py
ddnatlas/parse_files.py
ddnatlas/primitives.py
ddnatlas/queries.py
ddnatlas/relationships.py
ddnatlas/scalars.py
ddnatlas/supergraph_atlas_types.py
ddnatlas/supergraph_types.json
ddnatlas/update.py
ddnatlas/update_entities.py
ddnatlas-0.1.8.dist-info/LICENSE
ddnatlas-0.1.8.dist-info/METADATA
ddnatlas-0.1.8.dist-info/WHEEL
ddnatlas-0.1.8.dist-info/entry_points.txt
ddnatlas-0.1.8.dist-info/RECORD
